pytest_tuitest/__init__.py
pytest_tuitest/colors.py
pytest_tuitest/plugin.py
pytest_tuitest/process.py
pytest_tuitest/styles.py
pytest_tuitest/terminal.py
pytest_tuitest-0.1.0.dist-info/entry_points.txt
pytest_tuitest-0.1.0.dist-info/licenses/LICENSE
pytest_tuitest-0.1.0.dist-info/WHEEL
pytest_tuitest-0.1.0.dist-info/METADATA
pytest_tuitest-0.1.0.dist-info/RECORD
