Metadata-Version: 2.4
Name: pytest-tuitest
Version: 0.1.0
Summary: pytest plugin for testing TUI and regular command-line applications.
Keywords: pytest,tui
Author: Milomir Babic (redant333)
Classifier: Framework :: Pytest
Classifier: Intended Audience :: Developers
Classifier: License :: OSI Approved :: MIT License
Classifier: Operating System :: POSIX
Classifier: Topic :: Software Development :: Quality Assurance
Classifier: Topic :: Software Development :: Testing
Classifier: Topic :: Utilities
License-File: LICENSE
Requires-Dist: pytest>=7.4.0
Requires-Dist: pyte>=0.8.1
Requires-Dist: flit>=3.9.0 ; extra == "dev"
Requires-Dist: pre-commit>=3.3.3 ; extra == "dev"
Requires-Dist: pylint>=2.17.5 ; extra == "dev"
Requires-Dist: pdoc==15.0.1 ; extra == "dev"
Project-URL: Documentation, https://redant333.github.io/pytest-tuitest/
Project-URL: Source, https://github.com/redant333/pytest-tuitest
Provides-Extra: dev
